Metadata-Version: 1.0
Name: taigacli
Version: 0.1.0
Summary: Command line interface to Taiga
Home-page: https://github.com/Indev-Group/taiga_cli
Author: Alksey Cherepanov
Author-email: ftp27host@gmail.com
License: MIT
Platform: UNKNOWN
